[
 {
  "platform": "Android",
  "rating": 5,
  "content": "Great! keeps my mind occupied",
  "version": "1.1.0",
  "country": "us",
  "id": "1db5e533-5801-4967-9b90-6d6fa64d9d48"
 },
 {
  "platform": "Android",
  "rating": 5,
  "content": "love this game",
  "version": "1.1.0",
  "country": "us",
  "id": "7607a90b-1864-42ad-8573-54a08a3154f3"
 },
 {
  "platform": "Android",
  "rating": 5,
  "content": "Great Game.",
  "version": "1.1.0",
  "country": "us",
  "id": "22f0324b-4f71-4b2e-89b7-42c019871029"
 },
 {
  "platform": "Android",
  "rating": 5,
  "content": "The only game I played for three days I loved the graphics because I like Egyptian things and you did a great job! ***** 5 stars",
  "version": "1.0.25",
  "country": "us",
  "id": "b328eed2-dfe2-4d00-a260-afd09a4c5a54"
 },
 {
  "platform": "Android",
  "rating": 5,
  "content": "this game very useful to me",
  "version": "1.0.24",
  "country": "us",
  "id": "459cbec9-77e0-4b38-af9e-0346f27c2f0d"
 },
 {
  "platform": "Android",
  "rating": 5,
  "content": "My favorite game",
  "version": "1.0.24",
  "country": "us",
  "id": "9447b6ca-b4d5-4ff1-853a-d885d15872ab"
 },
 {
  "platform": "Android",
  "rating": 5,
  "content": "Best game",
  "version": "1.0.25",
  "country": "us",
  "id": "d0832b8d-f5bd-42ea-bb1e-76d964cab3bf"
 },
 {
  "platform": "Android",
  "rating": 5,
  "content": "Love this",
  "version": "1.0.25",
  "country": "us",
  "id": "12fe485b-b70c-43f7-b953-5514c62a7c9c"
 },
 {
  "platform": "Android",
  "rating": 5,
  "content": "love this game",
  "version": "1.0.24",
  "country": "us",
  "id": "0326265d-bb99-4c31-a087-bcac1434b9ba"
 },
 {
  "platform": "Android",
  "rating": 5,
  "content": "I love this game, but I have to say that the ads I've been seeing on YouTube are not the way I've seen any of the game sets unless they are further in the game and I haven't gotten to them yet.",
  "version": "1.0.24",
  "country": "us",
  "id": "02eaf0db-b63e-425c-949b-87a5a743b03f"
 },
 {
  "platform": "Android",
  "rating": 5,
  "content": "brilliant graphics lovely game",
  "version": "1.0.25",
  "country": "us",
  "id": "6052a349-f8cd-4230-97a1-86fff67a23cd"
 },
 {
  "platform": "Android",
  "rating": 5,
  "content": "brilliant!",
  "version": "1.0.25",
  "country": "us",
  "id": "457236e2-ead1-426c-a9f0-4e4c3e01295a"
 },
 {
  "platform": "Android",
  "rating": 5,
  "content": "very good good",
  "version": "1.0.25",
  "country": "us",
  "id": "be1e7a68-d8cf-4e44-a105-fc8b2e473327"
 },
 {
  "platform": "Android",
  "rating": 5,
  "content": "Y'all gotta install this game! It's fast and furious! Colorfully magnificent! Classy and bold💫💫💫💫💫 I am editing my review today 6/17/26 After I finish a game and choose to watch your ad for extra coins....after watching ad then instead of giving me my reward you skip the reward by starting me all over! bummer! hurts my feelings like a lot🥲😔",
  "version": "1.0.25",
  "country": "us",
  "id": "936d0832-cdbf-419f-9f8d-49fbb6cd20c4"
 },
 {
  "platform": "Android",
  "rating": 5,
  "content": "😊🥰",
  "version": "1.0.25",
  "country": "us",
  "id": "033e5895-ab5a-4f8d-961a-7a7706ecbbf9"
 },
 {
  "platform": "Android",
  "rating": 1,
  "content": "forced ads",
  "version": "1.0.24",
  "country": "us",
  "id": "99c57291-ee7e-4f0a-b439-e8aba4b734b8"
 },
 {
  "platform": "Android",
  "rating": 4,
  "content": "Best Brain game",
  "version": "1.0.20",
  "country": "us",
  "id": "e76619d7-5903-4010-9c76-97e410ebd3d0"
 },
 {
  "platform": "Android",
  "rating": 5,
  "content": "I am really enjoying this game it's colourful most of these games for boring but this one is not",
  "version": "1.0.24",
  "country": "us",
  "id": "12d26342-01d3-4e6c-a017-bfa592f2fd17"
 },
 {
  "platform": "Android",
  "rating": 3,
  "content": "I would like this much better if you could turn off the guy that keeps saying great",
  "version": "1.0.25",
  "country": "us",
  "id": "5b2c307d-de6a-4455-9799-98566463b3d2"
 },
 {
  "platform": "Android",
  "rating": 4,
  "content": "All good so far.",
  "version": "1.0.25",
  "country": "us",
  "id": "31cdb87f-3f79-4fc6-8d42-f819160c8610"
 },
 {
  "platform": "Android",
  "rating": 5,
  "content": "fun game and relaxing",
  "version": "1.0.25",
  "country": "us",
  "id": "fb498892-b3d2-4c59-b695-debc1d5ba3c1"
 },
 {
  "platform": "Android",
  "rating": 5,
  "content": "I like this game,it calms my mind and it's challenging enough not to get bored.",
  "version": "1.0.24",
  "country": "us",
  "id": "5ea3c9e3-263c-4e67-bcb2-e07498cdaff7"
 },
 {
  "platform": "Android",
  "rating": 5,
  "content": "Game very Good and funny.",
  "version": "1.0.22",
  "country": "us",
  "id": "e2159dcb-0edb-4aaf-8f61-8a7505c5f7ad"
 },
 {
  "platform": "Android",
  "rating": 5,
  "content": "I really enjoy this game it so fun their graffiti are so good I absolutely 💯 ❤️ the game im giving them a 5 star 🌟 love it",
  "version": "1.0.24",
  "country": "us",
  "id": "ef595c1c-bafe-4099-bd4c-d1a9513ff932"
 },
 {
  "platform": "Android",
  "rating": 5,
  "content": "very challenging and alot of fun",
  "version": "1.0.24",
  "country": "us",
  "id": "b8e368eb-d246-43ad-8963-8e1cd2ace7d8"
 },
 {
  "platform": "Android",
  "rating": 5,
  "content": "brilliant graphics early days yet, seems to be a very good game.",
  "version": "1.0.24",
  "country": "us",
  "id": "24ce692b-fdc1-41dc-a918-33c60800c243"
 },
 {
  "platform": "Android",
  "rating": 5,
  "content": "this is a great game very challenging!",
  "version": "1.0.23",
  "country": "us",
  "id": "0ef901fa-7eb3-4988-8861-eca6e61f0749"
 },
 {
  "platform": "Android",
  "rating": 2,
  "content": "was enjoying the game until I reached level 116 and it's impossible to carry on because when you put 3 anubis heads on the bar above, they stay there. I've tried everything to get rid of them over 3/4 days and if you've already got objects or need to add more to carry on, end of game. I would've put more stars but this level has been rather frustrating and taken the enjoyment out of it",
  "version": "1.0.24",
  "country": "us",
  "id": "6fcca3e2-5efd-47f8-9fca-efbd42e5643a"
 },
 {
  "platform": "Android",
  "rating": 5,
  "content": "I live this game",
  "version": "1.0.23",
  "country": "us",
  "id": "618cb846-f41d-43d7-80a5-64bcdf07228c"
 },
 {
  "platform": "Android",
  "rating": 5,
  "content": "Enjoyable",
  "version": "1.0.24",
  "country": "us",
  "id": "8b2f1391-a865-4a76-8c52-c8141f8c326a"
 },
 {
  "platform": "Android",
  "rating": 3,
  "content": "too many videos in between every win",
  "version": "1.0.24",
  "country": "us",
  "id": "d1d17caa-21d1-4899-bb5f-aeb3a4d937c2"
 },
 {
  "platform": "Android",
  "rating": 4,
  "content": "Fun game",
  "version": "1.0.23",
  "country": "us",
  "id": "bb4db857-2c6f-4c11-8616-8eef8e54fe05"
 },
 {
  "platform": "Android",
  "rating": 5,
  "content": "good",
  "version": "1.0.24",
  "country": "us",
  "id": "360b2a64-fc23-4008-86df-4ac65b931848"
 },
 {
  "platform": "Android",
  "rating": 5,
  "content": "love this game so relaxing and fun",
  "version": "1.0.24",
  "country": "us",
  "id": "2bb0dcf6-77e1-4f97-b995-cbbcc01b6fe4"
 },
 {
  "platform": "Android",
  "rating": 5,
  "content": "Great 👍🏽😸",
  "version": "1.0.23",
  "country": "us",
  "id": "7bc84eca-5b65-4672-8c7e-1996de65778f"
 },
 {
  "platform": "Android",
  "rating": 5,
  "content": "best good game 👍💪",
  "version": "1.0.23",
  "country": "us",
  "id": "3984359b-7c80-4b41-b555-f7d4341cb43e"
 },
 {
  "platform": "Android",
  "rating": 5,
  "content": "brilliant",
  "version": "1.0.23",
  "country": "us",
  "id": "97cf895d-5f03-40d8-8474-d3cb7acc890f"
 },
 {
  "platform": "Android",
  "rating": 5,
  "content": "Awesome!!",
  "version": "1.0.23",
  "country": "us",
  "id": "5b5f9f20-0244-4574-b4b5-cc8d48c50503"
 },
 {
  "platform": "Android",
  "rating": 5,
  "content": "A great game to play.",
  "version": "1.0.23",
  "country": "us",
  "id": "6128ccd4-4f7f-4d9b-a3cc-579e403af601"
 },
 {
  "platform": "Android",
  "rating": 1,
  "content": "SOOOOO many ads. 5.00 a month for no ads. Good game but not worth it. UNINSTALL DON'T PLAY. I watch ads for prize it's not real. BUY BUY BUY",
  "version": "1.0.22",
  "country": "us",
  "id": "e3f546f4-bbf1-42d3-8da5-eca4266580b8"
 },
 {
  "platform": "Android",
  "rating": 5,
  "content": "👍",
  "version": "1.0.23",
  "country": "us",
  "id": "fead1e44-2832-4c84-b1e8-04def1dca125"
 },
 {
  "platform": "Android",
  "rating": 5,
  "content": "I like it",
  "version": "1.0.23",
  "country": "us",
  "id": "ae7eb152-14e2-45c3-8536-27a005051aad"
 },
 {
  "platform": "Android",
  "rating": 5,
  "content": "it's matchable it's fast pace and it's fun worth the download because the download fast and there's no ads when you use your tablet you don't even need airplane mode I highly recommend this game for many reasons thumbs up to the game developers and thanks for having this available",
  "version": "1.0.22",
  "country": "us",
  "id": "3626a467-9ef5-45ab-9635-947553fec655"
 },
 {
  "platform": "Android",
  "rating": 5,
  "content": "visually awesome and the game is very enjoyable.",
  "version": "1.0.22",
  "country": "us",
  "id": "477558c1-5705-406b-a5f0-94a80675c228"
 },
 {
  "platform": "Android",
  "rating": 5,
  "content": "it's really Good",
  "version": "1.0.22",
  "country": "us",
  "id": "1caddfd5-7acf-4c29-a21d-bda7ebc65eaa"
 },
 {
  "platform": "Android",
  "rating": 2,
  "content": "level 75 can't be done deleting tomorrow",
  "version": "1.0.22",
  "country": "us",
  "id": "3ddeeca6-5e76-4781-aac7-731f7632f29c"
 },
 {
  "platform": "Android",
  "rating": 5,
  "content": "It's a very fun and relaxing game!",
  "version": "1.0.22",
  "country": "us",
  "id": "d5f32b28-fe65-43a8-8e18-621227d06ade"
 },
 {
  "platform": "Android",
  "rating": 5,
  "content": "This very FUN & ADDICTIVE GAME!! 😘❤️❤️❤️💪💪❤️❤️",
  "version": "1.0.22",
  "country": "us",
  "id": "cccb6595-680f-46af-8578-1d27a6be08d6"
 },
 {
  "platform": "Android",
  "rating": 5,
  "content": "amusing and awesome",
  "version": "1.0.22",
  "country": "us",
  "id": "96b2e6c1-eadb-4f86-8b6d-3050bdcce719"
 },
 {
  "platform": "Android",
  "rating": 5,
  "content": "😎",
  "version": "1.0.22",
  "country": "us",
  "id": "c49fe185-cc4b-46b9-b394-398041354161"
 },
 {
  "platform": "Android",
  "rating": 5,
  "content": "this is a fantastic game. thank you!",
  "version": "1.0.22",
  "country": "us",
  "id": "ec6526b0-1307-4d94-9b91-6f682240703d"
 },
 {
  "platform": "Android",
  "rating": 5,
  "content": "love it keeps your brain thinking 🤔😀",
  "version": "1.0.22",
  "country": "us",
  "id": "59b46fc1-a24d-4a31-b458-bc00413d17a1"
 },
 {
  "platform": "Android",
  "rating": 1,
  "content": "I love this game, but the ads for bonus items are not working. For example, if I click on an ad for an undo button, I get 80 coins. if I click on an ad for 200 coins, I don't get anything.",
  "version": "1.0.22",
  "country": "us",
  "id": "7daf19a3-3fb9-475e-8f16-c82a715215e6"
 },
 {
  "platform": "Android",
  "rating": 5,
  "content": "awesome",
  "version": "1.0.22",
  "country": "us",
  "id": "fe4882ee-f5b0-4beb-90c8-b90eb9912831"
 },
 {
  "platform": "Android",
  "rating": 5,
  "content": "ممتازة جدا",
  "version": "1.0.22",
  "country": "us",
  "id": "7e3b7570-2be2-480b-bb0e-91d92f6dd90c"
 },
 {
  "platform": "Android",
  "rating": 5,
  "content": "I enjoy this game",
  "version": "1.0.22",
  "country": "us",
  "id": "55e542d1-f17b-440b-ab93-9e495ca92e0f"
 },
 {
  "platform": "Android",
  "rating": 5,
  "content": "love this game 🎯😄",
  "version": "1.0.22",
  "country": "us",
  "id": "f2d124e7-ed6d-4291-9a24-225f50495ae8"
 },
 {
  "platform": "Android",
  "rating": 5,
  "content": "good game to play",
  "version": "1.0.22",
  "country": "us",
  "id": "c3a49b9d-ac36-49f2-a6d1-bcffaea04aa7"
 },
 {
  "platform": "Android",
  "rating": 5,
  "content": "love the graphics. blessings",
  "version": "1.0.22",
  "country": "us",
  "id": "9b0fde24-c0d1-4217-a058-1634f0b0abb2"
 },
 {
  "platform": "Android",
  "rating": 5,
  "content": "Great game! very colorful and fun!",
  "version": "1.0.22",
  "country": "us",
  "id": "fb436a23-2cc3-4bb5-8697-1bf6da9c2604"
 },
 {
  "platform": "Android",
  "rating": 5,
  "content": "I started playing this game and now I can't stop..",
  "version": "1.0.22",
  "country": "us",
  "id": "81dfe45b-8558-466e-8a82-5cce6bfd54f5"
 },
 {
  "platform": "Android",
  "rating": 5,
  "content": "You can keep the quote for few more seconds .Not able to read fully and the game starts.",
  "version": "1.0.22",
  "country": "us",
  "id": "6918fec4-c282-4284-9d76-4cfa53cb5548"
 },
 {
  "platform": "Android",
  "rating": 5,
  "content": "great game",
  "version": "1.0.22",
  "country": "us",
  "id": "3c2371a1-48ed-42e1-bbdf-76ae556d8dc8"
 },
 {
  "platform": "Android",
  "rating": 5,
  "content": "good",
  "version": "1.0.22",
  "country": "us",
  "id": "16a7f303-e2f3-4008-82a5-eddb9c04bbf1"
 },
 {
  "platform": "Android",
  "rating": 1,
  "content": "Brilliant victory nice app try to",
  "version": "1.0.21",
  "country": "us",
  "id": "c53c7353-8e01-49cf-b2d3-e0289bb84d56"
 },
 {
  "platform": "Android",
  "rating": 5,
  "content": "I appreciate TILE Pyramid game is fun.",
  "version": "1.0.22",
  "country": "us",
  "id": "656f49f7-7d91-4705-a5e0-4b1a5bd2cc1e"
 },
 {
  "platform": "Android",
  "rating": 5,
  "content": "👍👍👍",
  "version": "1.0.22",
  "country": "us",
  "id": "903272d3-b98b-44b7-9496-3ad54efa3613"
 },
 {
  "platform": "Android",
  "rating": 5,
  "content": "Love the game",
  "version": "1.0.21",
  "country": "us",
  "id": "46c05d9a-2f87-4f99-bfca-47e9bdb966ab"
 },
 {
  "platform": "Android",
  "rating": 5,
  "content": "very good",
  "version": "1.0.21",
  "country": "us",
  "id": "3f77fafd-60ee-4fe0-9ee5-07db3bcd18e6"
 },
 {
  "platform": "Android",
  "rating": 5,
  "content": "the game is addictive but to many adds",
  "version": "1.0.21",
  "country": "us",
  "id": "88f6201b-6557-4a98-8db1-fcfdc2fa81c4"
 },
 {
  "platform": "Android",
  "rating": 5,
  "content": "best game ever",
  "version": "1.0.21",
  "country": "us",
  "id": "01f21134-72bf-49e7-836a-ba7439d9c250"
 },
 {
  "platform": "Android",
  "rating": 5,
  "content": "it is good fun too play sign Merlin",
  "version": "1.0.21",
  "country": "us",
  "id": "f6d813b5-5225-4ada-b157-b6d422f6de35"
 },
 {
  "platform": "Android",
  "rating": 3,
  "content": "this game is fun, however, it is NOTHING like the ad for the game. very disappointing!! 😕",
  "version": "1.0.19",
  "country": "us",
  "id": "1f230414-5b37-4418-a8c4-1b35d79f9d87"
 },
 {
  "platform": "Android",
  "rating": 5,
  "content": "great new game....thanks",
  "version": "1.0.21",
  "country": "us",
  "id": "a56d5023-056b-4bb1-a5eb-de308e40352b"
 },
 {
  "platform": "Android",
  "rating": 1,
  "content": "boring each level is the same",
  "version": "1.0.21",
  "country": "us",
  "id": "c372b5b8-4d44-4877-9a08-63cb99bc476c"
 },
 {
  "platform": "Android",
  "rating": 5,
  "content": "awsome.relaxing.calming to the nerves.tks.",
  "version": "1.0.20",
  "country": "us",
  "id": "145a7775-6a5c-4378-a44e-bb8d378d6922"
 },
 {
  "platform": "Android",
  "rating": 5,
  "content": "good game",
  "version": "1.0.20",
  "country": "us",
  "id": "616da316-ad47-403e-b73a-7deb6ce535bf"
 },
 {
  "platform": "Android",
  "rating": 5,
  "content": "Amazing the music is stunning it makes you enjoy the game more, 👍👍👍👍👍👍👍👍👍❤️❤️❤️❤️❤️",
  "version": "1.0.20",
  "country": "us",
  "id": "4ee3ff1c-8c1b-4f2b-82d8-0926c21da8cc"
 },
 {
  "platform": "Android",
  "rating": 5,
  "content": "Fun game to play",
  "version": "1.0.21",
  "country": "us",
  "id": "4788f10c-3840-4f29-a223-e76ec9af9d6c"
 },
 {
  "platform": "Android",
  "rating": 5,
  "content": "great game l love it",
  "version": "1.0.20",
  "country": "us",
  "id": "1b527556-97ae-4385-93e0-3f1a449040ef"
 },
 {
  "platform": "Android",
  "rating": 5,
  "content": "very challenging.",
  "version": "1.0.21",
  "country": "us",
  "id": "87262940-5cad-4c00-b34e-bf85295e632f"
 },
 {
  "platform": "Android",
  "rating": 5,
  "content": "fun little game. I'm enjoying it",
  "version": "1.0.20",
  "country": "us",
  "id": "2d3148cc-6d31-4de4-b3b0-efbcba6e5c17"
 },
 {
  "platform": "Android",
  "rating": 3,
  "content": "Just got tired of looking at the same tile set. uninstall",
  "version": "1.0.19",
  "country": "us",
  "id": "c1be561f-e8b9-4aed-b405-1a6be91ec279"
 },
 {
  "platform": "Android",
  "rating": 5,
  "content": "I love this game.",
  "version": "1.0.19",
  "country": "us",
  "id": "4d77787b-eec5-4f72-b665-3df063c99db3"
 },
 {
  "platform": "Android",
  "rating": 5,
  "content": "it's alright...for now!! i",
  "version": "1.0.20",
  "country": "us",
  "id": "6af6b5ca-e09a-49c5-8ae8-5b6adfeb8287"
 },
 {
  "platform": "Android",
  "rating": 5,
  "content": "good game",
  "version": "1.0.19",
  "country": "us",
  "id": "e911ec99-0959-4a27-8e6c-b7dffb70fe5b"
 },
 {
  "platform": "Android",
  "rating": 5,
  "content": "good",
  "version": "1.0.20",
  "country": "us",
  "id": "d86094c8-23f6-4a4d-9f0b-5818eecf03f9"
 },
 {
  "platform": "Android",
  "rating": 5,
  "content": "nice I",
  "version": "1.0.20",
  "country": "us",
  "id": "5565a404-f245-4d7e-b08c-14eeaa424515"
 },
 {
  "platform": "Android",
  "rating": 5,
  "content": "Cool",
  "version": "1.0.19",
  "country": "us",
  "id": "dfea0159-11d9-49e0-9e25-25a05dbb4a47"
 },
 {
  "platform": "Android",
  "rating": 5,
  "content": "totally love the graphics. the colors and images are very visually appealing",
  "version": "",
  "country": "us",
  "id": "987733c0-78b1-49d8-b152-9c587d5f503a"
 },
 {
  "platform": "Android",
  "rating": 5,
  "content": "im addicted to this game I'm on level 300",
  "version": "1.0.18",
  "country": "us",
  "id": "d91cdf50-bb5b-4d4b-b257-5d2e483af0c4"
 },
 {
  "platform": "Android",
  "rating": 2,
  "content": "it looks like it would be fun BUT, after installed INSTEAD of just letting you look around the board and play it constantly flashes matches, irritating. No way to deselect it no options. I'm a very good and fast majong player. I just wanted cute & Relaxing. had to uninstall 😒",
  "version": "1.0.19",
  "country": "us",
  "id": "8d6830fc-cfc7-4206-898f-6dc7f7c81c66"
 },
 {
  "platform": "Android",
  "rating": 5,
  "content": "having me some fun",
  "version": "1.0.13",
  "country": "us",
  "id": "71daf6d5-66ae-48d9-b307-5c9eb99147be"
 },
 {
  "platform": "Android",
  "rating": 5,
  "content": "brillllllllliant",
  "version": "1.0.15",
  "country": "us",
  "id": "2cc2b999-edfa-4480-bebf-d2626a818d0e"
 },
 {
  "platform": "Android",
  "rating": 5,
  "content": "very addictive 😍",
  "version": "1.0.13",
  "country": "us",
  "id": "ccf4e982-51c1-49b4-a1ab-cf3b5c5383d5"
 },
 {
  "platform": "Android",
  "rating": 1,
  "content": "not enough points to keep going",
  "version": "1.0.13",
  "country": "us",
  "id": "a55d4e15-01bc-442c-99dd-05d036110625"
 },
 {
  "platform": "Android",
  "rating": 5,
  "content": "I like it is good.",
  "version": "1.0.13",
  "country": "us",
  "id": "3944e7dc-cc24-424c-a4f9-cd11edaa8f4a"
 },
 {
  "platform": "Android",
  "rating": 5,
  "content": "so far, good, so petty",
  "version": "1.0.14",
  "country": "us",
  "id": "21529079-0b08-4570-b718-553eff30b21f"
 },
 {
  "platform": "Android",
  "rating": 3,
  "content": "what's with the annoying condescending pop-ups before every game? it's so negative ...i enjoy this game...love the graphics & music, but those negative remarks before each game make me want to uninstall it. No one needs negativity in this world! Just want to play a silly game!! those negative remarks are new.....a BAD upgrade IMO!!",
  "version": "1.0.14",
  "country": "us",
  "id": "107bb283-cc3b-4b84-a76e-2ae0d8f9ae44"
 },
 {
  "platform": "Android",
  "rating": 1,
  "content": "Your game would be awesome if it weren't for all the crummy ads after EVERY GAME 😡😡REDICULOUS!!!!☹️👎UNINSTALLING!!!!!",
  "version": "1.0.13",
  "country": "us",
  "id": "86aa7dac-22d2-4e52-91c5-b9332b575e7c"
 },
 {
  "platform": "Android",
  "rating": 5,
  "content": "গুড",
  "version": "1.0.13",
  "country": "us",
  "id": "727f239c-667f-480a-9241-c1e3e94e6680"
 },
 {
  "platform": "Android",
  "rating": 5,
  "content": "Thanks My Dearest Dear Dear Friend Introducing Different Types Of Wonderful Designed Games. 💯 Mark's And Stars 5 🌟🌟🌟🌟🌟For Your Recommended Relaxation Reduce Stress Carefree Freedom Brain Times Lifestyle Appreciated For Your Hard Work Well Done Gd Jobs 👏 👏👏💖👍😘💕🥰",
  "version": "1.0.13",
  "country": "us",
  "id": "0196da94-5965-4189-9a69-1e6c918ea5d7"
 },
 {
  "platform": "Android",
  "rating": 2,
  "content": "in level 5 I had one space left on the collection bar a banner came up telling me to be careful only one spot left. the banner covered the first row of collectible items WHICH INCLUDED THE FEATHER I NEEDED TO COMPLETE THE SET OF THREE FEATHERS AND FORCED TO USE A POWER UP TO COMPLETE THE LEVEL. DELETED THE GAME. IT LOOKED LIKE IT MIGHT HAVE BEEN FUN. OH WELL",
  "version": "1.0.13",
  "country": "us",
  "id": "e3119c40-747f-47f8-92f8-fca1d64afbf5"
 },
 {
  "platform": "Android",
  "rating": 5,
  "content": "challenging and exciting",
  "version": "1.0.15",
  "country": "us",
  "id": "579db5bc-28b4-4cc0-9d4c-a41fd20cb7f5"
 },
 {
  "platform": "Android",
  "rating": 5,
  "content": "Awesome game. Stress free, stunning graphics and the Ads aren't too long.",
  "version": "1.0.14",
  "country": "us",
  "id": "2d52d89d-9a48-4909-b54e-689905c51da5"
 },
 {
  "platform": "Android",
  "rating": 5,
  "content": "This is more relaxing than the one I played before 😀💖☕",
  "version": "1.0.15",
  "country": "us",
  "id": "c8412bc1-76d5-4702-8b1e-dded099a9722"
 },
 {
  "platform": "Android",
  "rating": 5,
  "content": "Most enjoyable and relaxing. Escape from tension. Thank you.",
  "version": "1.0.14",
  "country": "us",
  "id": "6402518f-ca81-45ad-80f7-f1e6432b33f7"
 },
 {
  "platform": "Android",
  "rating": 5,
  "content": "a great game",
  "version": "",
  "country": "us",
  "id": "88b46d80-2ae6-4279-bca4-51a83835d2ec"
 },
 {
  "platform": "Android",
  "rating": 5,
  "content": "This is just a really fun game. I'm an ancient history buff, so it's especially fun for me. The tiles are cute and colorful, and the graphics in general are lovely, and fairly accirate.",
  "version": "1.0.13",
  "country": "us",
  "id": "d433230f-8379-4dda-808a-84c927fb0544"
 },
 {
  "platform": "Android",
  "rating": 5,
  "content": "nice graphics and good gaming.",
  "version": "1.0.13",
  "country": "us",
  "id": "1d93c122-747c-4034-80b8-5a0ff3b58fb0"
 },
 {
  "platform": "Android",
  "rating": 5,
  "content": "great game",
  "version": "1.0.14",
  "country": "us",
  "id": "2b52d4a6-dea6-4016-8a3e-5f4a9cbd228f"
 },
 {
  "platform": "Android",
  "rating": 2,
  "content": "the game play is not as advertised prefer the advertisment",
  "version": "",
  "country": "us",
  "id": "0488f0db-94cd-482c-ae6b-a938aa56bb2b"
 },
 {
  "platform": "Android",
  "rating": 1,
  "content": "not worth downloading",
  "version": "",
  "country": "us",
  "id": "2c77e75e-dd23-48bd-b709-6a1450b02075"
 },
 {
  "platform": "Android",
  "rating": 5,
  "content": "I Really Like and Love This Cute 🥰 A Lot! I Really Like and Love The Music 🎵🎶🎵🎶🎵🎶🎵 Too! It's a Relaxing Game To Play It On a Sunny ☀️ Or Rainy 🌧️ Day ! Love 🥰 It 🥰 Great 👍 Job Guy's 👏",
  "version": "1.0.13",
  "country": "us",
  "id": "0a310194-1f27-4de1-b610-60bb02d375fd"
 },
 {
  "platform": "Android",
  "rating": 5,
  "content": "very invigorating and the graphics are clear and sharp and it keeps your mind and brain active 😀",
  "version": "",
  "country": "us",
  "id": "c8f55f52-6f67-45da-9db6-794ad200c0c7"
 },
 {
  "platform": "Android",
  "rating": 5,
  "content": "L.OVE THIS GAME",
  "version": "1.0.13",
  "country": "us",
  "id": "4aee69d4-3e83-4a51-a222-faee90da2d4b"
 },
 {
  "platform": "Android",
  "rating": 5,
  "content": "nice, injoyed. thank you 👍",
  "version": "1.0.13",
  "country": "us",
  "id": "dd16b860-c059-4bf3-87cc-bedd73e3fba8"
 },
 {
  "platform": "Android",
  "rating": 3,
  "content": "beautiful but ordinary 😭😭😭😭 mahjong.",
  "version": "",
  "country": "us",
  "id": "059a2ef6-d88f-4098-9a2f-f9407e424962"
 },
 {
  "platform": "Android",
  "rating": 5,
  "content": "good game fun to play",
  "version": "1.0.13",
  "country": "us",
  "id": "ca176431-ac22-477d-b59b-2f302969381e"
 },
 {
  "platform": "Android",
  "rating": 5,
  "content": "anyone stucked on level 552? 😭",
  "version": "1.0.11",
  "country": "us",
  "id": "8ab83720-90d3-471c-afa9-759a3eadc7a6"
 },
 {
  "platform": "Android",
  "rating": 5,
  "content": "good game to play",
  "version": "1.0.13",
  "country": "us",
  "id": "c39faee5-36ce-4068-b2f0-984e1247aee9"
 },
 {
  "platform": "Android",
  "rating": 5,
  "content": "Great Fun !!",
  "version": "",
  "country": "us",
  "id": "c3289d3b-9532-402b-9d20-0f23c6c62cb8"
 },
 {
  "platform": "Android",
  "rating": 5,
  "content": "love it ,❤️",
  "version": "1.0.13",
  "country": "us",
  "id": "9102e12b-657c-410b-9181-1750048c58c8"
 },
 {
  "platform": "Android",
  "rating": 5,
  "content": "grandkids love it",
  "version": "1.0.13",
  "country": "us",
  "id": "de8b671f-4506-479a-996c-f46b50de1a81"
 },
 {
  "platform": "Android",
  "rating": 1,
  "content": "Don't waste your time, the game itself is great but not good enough to compensate for the ads you're forced to watch! There's an ad after every level - and sure, there's an exit button you can tap to 'opt out' of each ad but to do so you have to wait and exit multiple screens to get back to the game. Time it yourself - exiting out of all those screens takes just as long as just waiting through the full ad. I'm not supporting a game that expects me to spend more time on ads than on play.",
  "version": "",
  "country": "us",
  "id": "59645dd8-a816-4a57-9eaf-197068f48256"
 },
 {
  "platform": "Android",
  "rating": 2,
  "content": "this game could be a very good game except it's not giving me the money I earn on my spins and things..I'm going to give it one more week if this is not fixed by then..I'll delete..and I know it's not the device I play it on because nothing else is having trouble just this game, if it gets better I'll update my review",
  "version": "1.0.13",
  "country": "us",
  "id": "8decef47-8b1f-42b1-b63c-ad8b6fa32918"
 },
 {
  "platform": "Android",
  "rating": 5,
  "content": "I love playing this game.",
  "version": "1.0.13",
  "country": "us",
  "id": "0065312f-4dae-4f7f-a3c5-c0b872aff43f"
 },
 {
  "platform": "Android",
  "rating": 5,
  "content": "love this game",
  "version": "1.0.13",
  "country": "us",
  "id": "73bda885-8c98-4fbd-ab4b-c9b10896efee"
 },
 {
  "platform": "Android",
  "rating": 5,
  "content": "I love it 😀 😍",
  "version": "1.0.13",
  "country": "us",
  "id": "490d4880-766b-4d99-a8d9-8bf35c87a435"
 },
 {
  "platform": "Android",
  "rating": 5,
  "content": "well done",
  "version": "1.0.12",
  "country": "us",
  "id": "c8083c16-ae77-460e-bb9a-ee4a569d8882"
 },
 {
  "platform": "Android",
  "rating": 3,
  "content": "Can't play game, just keep matching tiles, very discouraged.",
  "version": "1.0.13",
  "country": "us",
  "id": "03cc0c4c-64c6-4591-a5de-3b726763d963"
 },
 {
  "platform": "Android",
  "rating": 5,
  "content": "very interesting, Egyptoloy is fantastic!🤩",
  "version": "1.0.10",
  "country": "us",
  "id": "644dcfea-0766-40a0-9f03-387a61597799"
 },
 {
  "platform": "Android",
  "rating": 5,
  "content": "good for the mind",
  "version": "1.0.12",
  "country": "us",
  "id": "89d71427-dfc6-4400-9244-5c7b8d728c86"
 },
 {
  "platform": "Android",
  "rating": 5,
  "content": "Great game, I am enjoying no adverts",
  "version": "1.0.11",
  "country": "us",
  "id": "5c5e065b-f40f-405f-91ca-bd14efd32fab"
 },
 {
  "platform": "Android",
  "rating": 5,
  "content": "good",
  "version": "1.0.11",
  "country": "us",
  "id": "6da44f83-be10-443e-80d6-106b054e20a9"
 },
 {
  "platform": "Android",
  "rating": 5,
  "content": "It's fun so far. I'll update later.",
  "version": "1.0.11",
  "country": "us",
  "id": "f9249e83-4cfd-4de9-82e4-d8c720cc0295"
 },
 {
  "platform": "Android",
  "rating": 5,
  "content": "outstanding",
  "version": "1.0.11",
  "country": "us",
  "id": "9e2162d0-53fa-4563-8581-dce92a64aace"
 },
 {
  "platform": "Android",
  "rating": 5,
  "content": "Great graphics challenging questions 0",
  "version": "1.0.11",
  "country": "us",
  "id": "41911668-d7cb-4702-823a-f1c7df767d8b"
 },
 {
  "platform": "Android",
  "rating": 5,
  "content": "interesting Game with wonderful exciting levels...play for sure !!!!!",
  "version": "1.0.9",
  "country": "us",
  "id": "285ce519-002a-43eb-b55b-e883f4d2de53"
 },
 {
  "platform": "Android",
  "rating": 5,
  "content": "ভালো খুব valo",
  "version": "1.0.10",
  "country": "us",
  "id": "64c6be4c-f0f9-4a20-8ddc-80a176cd5a35"
 },
 {
  "platform": "Android",
  "rating": 5,
  "content": "I love the Egyptian icons. blessings!",
  "version": "1.0.10",
  "country": "us",
  "id": "6c3108d6-1f35-40b1-bdbf-2495b2933809"
 },
 {
  "platform": "Android",
  "rating": 5,
  "content": "Awesome 👌",
  "version": "1.0.10",
  "country": "us",
  "id": "127b2d60-c506-44b3-93fa-623ec6cc0024"
 },
 {
  "platform": "Android",
  "rating": 4,
  "content": "easy and fun 😊",
  "version": "1.0.10",
  "country": "us",
  "id": "28d22916-2e76-445e-9e8e-780a47fe747e"
 },
 {
  "platform": "Android",
  "rating": 5,
  "content": "fun and relaxing",
  "version": "1.0.10",
  "country": "us",
  "id": "6bad1000-6dd2-4a62-8247-fdf52062d48b"
 },
 {
  "platform": "Android",
  "rating": 5,
  "content": "So Cute",
  "version": "1.0.10",
  "country": "us",
  "id": "cdefdf36-4ff2-4101-8022-32a1e4c0f9bb"
 },
 {
  "platform": "Android",
  "rating": 4,
  "content": "I like this game but wayyy too many add .. 4 stars...Thank You !",
  "version": "",
  "country": "us",
  "id": "6e2ef358-fce0-47c7-8ef0-fb8974977c23"
 },
 {
  "platform": "Android",
  "rating": 5,
  "content": "A Fun way to play Mahjong Tiles. large Titles, And It's So cute. Very Happy",
  "version": "1.0.9",
  "country": "us",
  "id": "a5a093f0-68e0-44a1-8617-227ccb9663d8"
 },
 {
  "platform": "Android",
  "rating": 1,
  "content": "I really like this game but I'm deleting bcuz it has to many ads. Maybe u would have more players if u had less ads.",
  "version": "1.0.10",
  "country": "us",
  "id": "ac2fc008-0c6b-49fc-a349-0cb1a0f225fb"
 },
 {
  "platform": "Android",
  "rating": 5,
  "content": "a very good relaxing game to play with and l tell any people to have a go at the pyramid game if they want play this game it is a relaxing game to play with l am enjoying the game",
  "version": "1.0.10",
  "country": "us",
  "id": "4a0effd8-9a09-4838-a121-8ded3e713653"
 },
 {
  "platform": "Android",
  "rating": 5,
  "content": "bahut hi achcha game hai",
  "version": "1.0.10",
  "country": "us",
  "id": "39c1945a-e85c-4b2e-8562-5148c56627b1"
 },
 {
  "platform": "Android",
  "rating": 5,
  "content": "Love Egyptian themed games. Stronger Egyptian music would be nice though like in Time Warp Solitaire.",
  "version": "1.0.9",
  "country": "us",
  "id": "5be49a22-3756-4f0d-94d4-8da95874080d"
 },
 {
  "platform": "Android",
  "rating": 5,
  "content": "so much fun to play",
  "version": "1.0.9",
  "country": "us",
  "id": "0ff274f9-5748-4424-ae62-1c3e3f3f3dc4"
 },
 {
  "platform": "Android",
  "rating": 5,
  "content": "fun",
  "version": "1.0.9",
  "country": "us",
  "id": "db94e395-a0d5-4e85-a559-c5c40e14a7d6"
 },
 {
  "platform": "Android",
  "rating": 5,
  "content": "really good.",
  "version": "1.0.9",
  "country": "us",
  "id": "379951d6-1b79-4210-b644-53324fa9c467"
 },
 {
  "platform": "Android",
  "rating": 5,
  "content": "love the game",
  "version": "1.0.9",
  "country": "us",
  "id": "67c788db-26ff-4aa3-a48e-b505eb921b9a"
 },
 {
  "platform": "Android",
  "rating": 5,
  "content": "great!!",
  "version": "1.0.9",
  "country": "us",
  "id": "2d1a35f2-b456-4292-9a66-5b83c868c21e"
 },
 {
  "platform": "Android",
  "rating": 5,
  "content": "It's good.",
  "version": "1.0.8",
  "country": "us",
  "id": "ccabf9ea-d62d-480e-913f-1fb153626722"
 },
 {
  "platform": "Android",
  "rating": 5,
  "content": "good",
  "version": "1.0.8",
  "country": "us",
  "id": "60c47d2b-4c18-4acd-9623-bb381301eefb"
 },
 {
  "platform": "Android",
  "rating": 5,
  "content": "Most enjoyable and relaxing. Thank you.",
  "version": "1.0.8",
  "country": "us",
  "id": "9bab30f9-edb8-4c87-aa54-9669ae9c0470"
 },
 {
  "platform": "Android",
  "rating": 5,
  "content": "superb game",
  "version": "",
  "country": "us",
  "id": "c7eaa126-53a1-499a-95f8-db41fd51f259"
 },
 {
  "platform": "Android",
  "rating": 5,
  "content": "I think this is a very relaxing game .x",
  "version": "1.0.8",
  "country": "us",
  "id": "c0b4d27b-7be0-4dae-8200-857bd530baa0"
 },
 {
  "platform": "Android",
  "rating": 5,
  "content": "super game 😁",
  "version": "1.0.8",
  "country": "us",
  "id": "0d6b10fe-6d8d-40bc-a06f-319216dda4b5"
 },
 {
  "platform": "Android",
  "rating": 5,
  "content": "real exciting and relaxing game!!!!",
  "version": "1.0.8",
  "country": "us",
  "id": "19828d27-0981-4c24-a7b7-5c2809e1b885"
 },
 {
  "platform": "Android",
  "rating": 5,
  "content": "good game",
  "version": "1.0.8",
  "country": "us",
  "id": "cc8bbd52-be65-4376-8e43-d952390de93a"
 },
 {
  "platform": "Android",
  "rating": 5,
  "content": "supe",
  "version": "",
  "country": "us",
  "id": "c73c416f-5451-4a7e-875f-a13555ec2b24"
 },
 {
  "platform": "Android",
  "rating": 3,
  "content": "could be a good game but too many adverts & there's an advert that doesn't play just a black screen & doesn't go off I have to close the game down & restart the game",
  "version": "1.0.8",
  "country": "us",
  "id": "80fe1cbe-ea55-4dba-a86f-2956fec3b4cd"
 },
 {
  "platform": "Android",
  "rating": 5,
  "content": "Rather easy to play",
  "version": "1.0.8",
  "country": "us",
  "id": "79b5fdbb-b0a7-4a2c-a338-7879afc4928c"
 },
 {
  "platform": "Android",
  "rating": 5,
  "content": "This game is attractive. You literally have to learn pidgin English.",
  "version": "1.0.8",
  "country": "us",
  "id": "a6ea4259-946f-4a9b-ae96-249e7635ea99"
 },
 {
  "platform": "Android",
  "rating": 5,
  "content": "I really really love this game i have quite a lot of games on my phone but i always go back to this game every day Its a tile game but the tiles are not too far down and are easy accessable so you dont keep getting out The music is really pleasant too",
  "version": "1.0.6",
  "country": "us",
  "id": "55972462-63a4-4cf1-bfef-48c921eeb52c"
 },
 {
  "platform": "Android",
  "rating": 1,
  "content": "Malware. Virus. Pop up installed this and many other scam apps. Thumbs up if you agree. 👍🏻",
  "version": "",
  "country": "us",
  "id": "5433f266-56d4-444f-ab30-206d79cd3890"
 },
 {
  "platform": "Android",
  "rating": 2,
  "content": "wish it was less ads, like it was at the beginning levels. It was 1 ads for like every 4 games/ levels played and now it is after every single time you move up a level. I would give it more stars if it would have less ads",
  "version": "1.0.6",
  "country": "us",
  "id": "984747c0-caf5-4c35-a449-01ec4b81a4a3"
 },
 {
  "platform": "Android",
  "rating": 5,
  "content": "thank you so much is very helpful and fun",
  "version": "1.0.6",
  "country": "us",
  "id": "6300aae3-cf4d-4581-8235-e7ab5ee1f480"
 },
 {
  "platform": "Android",
  "rating": 4,
  "content": "enjoyable",
  "version": "1.0.4",
  "country": "us",
  "id": "ed0aa3f6-1864-4639-8365-d00c336cbe5d"
 },
 {
  "platform": "Android",
  "rating": 5,
  "content": "Brilliant game",
  "version": "1.0.4",
  "country": "us",
  "id": "126089f0-6cd0-4fb2-b72c-2c41318cc3cf"
 },
 {
  "platform": "Android",
  "rating": 5,
  "content": "its ok",
  "version": "1.0.2",
  "country": "us",
  "id": "49d3bca4-a2b4-4fde-b2bd-46f94973e1c8"
 },
 {
  "platform": "Android",
  "rating": 1,
  "content": "the men's voice is really annoying, quite patronising to be honest and that puts me off,shame cos I like the game. I know I can turn it off but then it's just music I like to ear the riles braking, and they are a bit small",
  "version": "1.0.2",
  "country": "us",
  "id": "be92e85d-3e60-4baa-9195-469ce1e29afb"
 },
 {
  "platform": "Android",
  "rating": 1,
  "content": "I love ❤️ Pyranid games, but the tiles are just too small because I have low vision. That's why I don't play a lot of your games because the tiles are just simply way to smal tiles are just way too small can't hardly see them.",
  "version": "1.0.2",
  "country": "us",
  "id": "1e447f11-dbe8-4c24-9abc-9fc25f7b6731"
 },
 {
  "platform": "Android",
  "rating": 4,
  "content": "Enjoyable game to play. Too many ads",
  "version": "1.0.1",
  "country": "us",
  "id": "188d5ec2-cc52-4fbb-af77-3470318d1473"
 },
 {
  "platform": "Android",
  "rating": 1,
  "content": "no dark mode",
  "version": "1.0.1",
  "country": "us",
  "id": "75c448d7-f952-48f3-ab77-2c32de2ee873"
 }
]