{
 "game": "tile_pyramid",
 "date": "2026-06-23",
 "is_first_run": true,
 "new_count": 198,
 "new_reviews": [
  {
   "platform": "iOS",
   "rating": 5,
   "content": "Love this game !!",
   "version": "1.1.0",
   "country": "us",
   "id": "14210707301"
  },
  {
   "platform": "iOS",
   "rating": 4,
   "content": "Good game, too many ads and needs to remove the voice from sound and just have the tile sounds.",
   "version": "1.0.14",
   "country": "us",
   "id": "14110483388"
  },
  {
   "platform": "iOS",
   "rating": 5,
   "content": "AriMONKEYS",
   "version": "1.0.11",
   "country": "us",
   "id": "14006250951"
  },
  {
   "platform": "iOS",
   "rating": 1,
   "content": "I paid $5.99 for no ads.  Now I have ads again.  Not happy.",
   "version": "1.0.11",
   "country": "us",
   "id": "13937484294"
  },
  {
   "platform": "iOS",
   "rating": 3,
   "content": "This game would be great if the  voice commentary  on almost every move could be silenced.",
   "version": "1.0.10",
   "country": "us",
   "id": "13929526079"
  },
  {
   "platform": "iOS",
   "rating": 5,
   "content": "Thumb up",
   "version": "1.0.10",
   "country": "us",
   "id": "13919500291"
  },
  {
   "platform": "iOS",
   "rating": 3,
   "content": "I really enjoy this game. Every once in a while I get the color changes to a solid color scheme. I love this but don’t know how it happens? Is it at a certain level?",
   "version": "1.0.9",
   "country": "us",
   "id": "13890448570"
  },
  {
   "platform": "iOS",
   "rating": 2,
   "content": "Tiles could be bigger. But having a good time thanks. Same request!!!",
   "version": "1.0.5",
   "country": "us",
   "id": "13832307639"
  },
  {
   "platform": "iOS",
   "rating": 5,
   "content": "👍🏿",
   "version": "1.0.3",
   "country": "us",
   "id": "13798371446"
  },
  {
   "platform": "iOS",
   "rating": 5,
   "content": "Exciting and Fun",
   "version": "1.0.3",
   "country": "us",
   "id": "13789291926"
  },
  {
   "platform": "iOS",
   "rating": 5,
   "content": "Game hay nha",
   "version": "1.0.7",
   "country": "vn",
   "id": "13859943362"
  },
  {
   "platform": "iOS",
   "rating": 5,
   "content": "Game đẹp, âm thanh hay, thao tác xịn",
   "version": "1.0.0",
   "country": "vn",
   "id": "13629210263"
  },
  {
   "platform": "iOS",
   "rating": 5,
   "content": "Good",
   "version": "1.0.14",
   "country": "gb",
   "id": "14096547534"
  },
  {
   "platform": "iOS",
   "rating": 5,
   "content": "Egypt is my favourite place in the world, so I love this game ,as it reminds me of wonderful holidays there.",
   "version": "1.0.1",
   "country": "gb",
   "id": "13716273055"
  },
  {
   "platform": "iOS",
   "rating": 4,
   "content": "It’s a great to relax to.",
   "version": "1.0.11",
   "country": "ca",
   "id": "13930854910"
  },
  {
   "platform": "iOS",
   "rating": 5,
   "content": "Literally every time I play this game I think about how I love the song so much that it makes me happy inside of my heart ❤️ and it’s so beautiful to me",
   "version": "1.0.10",
   "country": "ca",
   "id": "13919939281"
  },
  {
   "platform": "iOS",
   "rating": 2,
   "content": "It was nice to play initially but it seems that it was loaded with lots of advertisements after each level!\nThat’s far too silly to continue!",
   "version": "1.0.1",
   "country": "sg",
   "id": "13677059938"
  },
  {
   "platform": "iOS",
   "rating": 5,
   "content": "สนุกมาก",
   "version": "1.0.5",
   "country": "th",
   "id": "13840750293"
  },
  {
   "platform": "iOS",
   "rating": 5,
   "content": "見やすいし面白い",
   "version": "1.0.17",
   "country": "jp",
   "id": "14190587153"
  },
  {
   "platform": "Android",
   "rating": 5,
   "content": "Great! keeps my mind occupied",
   "version": "1.1.0",
   "country": "us",
   "id": "1db5e533-5801-4967-9b90-6d6fa64d9d48"
  },
  {
   "platform": "Android",
   "rating": 5,
   "content": "love this game",
   "version": "1.1.0",
   "country": "us",
   "id": "7607a90b-1864-42ad-8573-54a08a3154f3"
  },
  {
   "platform": "Android",
   "rating": 5,
   "content": "Great Game.",
   "version": "1.1.0",
   "country": "us",
   "id": "22f0324b-4f71-4b2e-89b7-42c019871029"
  },
  {
   "platform": "Android",
   "rating": 5,
   "content": "The only game I played for three days I loved the graphics because I like Egyptian things and you did a great job! ***** 5 stars",
   "version": "1.0.25",
   "country": "us",
   "id": "b328eed2-dfe2-4d00-a260-afd09a4c5a54"
  },
  {
   "platform": "Android",
   "rating": 5,
   "content": "this game very useful to me",
   "version": "1.0.24",
   "country": "us",
   "id": "459cbec9-77e0-4b38-af9e-0346f27c2f0d"
  },
  {
   "platform": "Android",
   "rating": 5,
   "content": "My favorite game",
   "version": "1.0.24",
   "country": "us",
   "id": "9447b6ca-b4d5-4ff1-853a-d885d15872ab"
  },
  {
   "platform": "Android",
   "rating": 5,
   "content": "Best game",
   "version": "1.0.25",
   "country": "us",
   "id": "d0832b8d-f5bd-42ea-bb1e-76d964cab3bf"
  },
  {
   "platform": "Android",
   "rating": 5,
   "content": "Love this",
   "version": "1.0.25",
   "country": "us",
   "id": "12fe485b-b70c-43f7-b953-5514c62a7c9c"
  },
  {
   "platform": "Android",
   "rating": 5,
   "content": "love this game",
   "version": "1.0.24",
   "country": "us",
   "id": "0326265d-bb99-4c31-a087-bcac1434b9ba"
  },
  {
   "platform": "Android",
   "rating": 5,
   "content": "I love this game, but I have to say that the ads I've been seeing on YouTube are not the way I've seen any of the game sets unless they are further in the game and I haven't gotten to them yet.",
   "version": "1.0.24",
   "country": "us",
   "id": "02eaf0db-b63e-425c-949b-87a5a743b03f"
  },
  {
   "platform": "Android",
   "rating": 5,
   "content": "brilliant graphics lovely game",
   "version": "1.0.25",
   "country": "us",
   "id": "6052a349-f8cd-4230-97a1-86fff67a23cd"
  },
  {
   "platform": "Android",
   "rating": 5,
   "content": "brilliant!",
   "version": "1.0.25",
   "country": "us",
   "id": "457236e2-ead1-426c-a9f0-4e4c3e01295a"
  },
  {
   "platform": "Android",
   "rating": 5,
   "content": "very good good",
   "version": "1.0.25",
   "country": "us",
   "id": "be1e7a68-d8cf-4e44-a105-fc8b2e473327"
  },
  {
   "platform": "Android",
   "rating": 5,
   "content": "Y'all gotta install this game! It's fast and furious! Colorfully magnificent! Classy and bold💫💫💫💫💫 I am editing my review today 6/17/26 After I finish a game and choose to watch your ad for extra coins....after watching ad then instead of giving me my reward you skip the reward by starting me all over! bummer! hurts my feelings like a lot🥲😔",
   "version": "1.0.25",
   "country": "us",
   "id": "936d0832-cdbf-419f-9f8d-49fbb6cd20c4"
  },
  {
   "platform": "Android",
   "rating": 5,
   "content": "😊🥰",
   "version": "1.0.25",
   "country": "us",
   "id": "033e5895-ab5a-4f8d-961a-7a7706ecbbf9"
  },
  {
   "platform": "Android",
   "rating": 1,
   "content": "forced ads",
   "version": "1.0.24",
   "country": "us",
   "id": "99c57291-ee7e-4f0a-b439-e8aba4b734b8"
  },
  {
   "platform": "Android",
   "rating": 4,
   "content": "Best Brain game",
   "version": "1.0.20",
   "country": "us",
   "id": "e76619d7-5903-4010-9c76-97e410ebd3d0"
  },
  {
   "platform": "Android",
   "rating": 5,
   "content": "I am really enjoying this game it's colourful most of these games for boring but this one is not",
   "version": "1.0.24",
   "country": "us",
   "id": "12d26342-01d3-4e6c-a017-bfa592f2fd17"
  },
  {
   "platform": "Android",
   "rating": 3,
   "content": "I would like this much better if you could turn off the guy that keeps saying great",
   "version": "1.0.25",
   "country": "us",
   "id": "5b2c307d-de6a-4455-9799-98566463b3d2"
  },
  {
   "platform": "Android",
   "rating": 4,
   "content": "All good so far.",
   "version": "1.0.25",
   "country": "us",
   "id": "31cdb87f-3f79-4fc6-8d42-f819160c8610"
  },
  {
   "platform": "Android",
   "rating": 5,
   "content": "fun game and relaxing",
   "version": "1.0.25",
   "country": "us",
   "id": "fb498892-b3d2-4c59-b695-debc1d5ba3c1"
  }
 ],
 "avg_now": 4.41,
 "avg_prev": null,
 "count_now": 198,
 "count_prev": null,
 "prev_date": null
}
